easycompression/__init__.py
easycompression-0.0.1.dist-info/METADATA
easycompression-0.0.1.dist-info/WHEEL
easycompression-0.0.1.dist-info/top_level.txt
easycompression-0.0.1.dist-info/RECORD
